Modulo_Digital/Lab3/sumador_4b.v
module sumador_4b (
    input  clk,   
    input  rst,
    input  [3:0] a_in, //4 bit
    input  [3:0] b_in, //4 bit
    input  cin_in,
    output reg  [3:0]  sum_out,
    output reg  cout_out
);

    wire [4:0] sum_temp; //cout_out & sum_out
    reg [3:0] a_reg, b_reg;
    reg cin_reg;

    // Operación combinacional del sumador
    assign sum_temp = a_reg + b_reg + cin_reg;

    always @(posedge clk) begin
        if (rst) begin
            //Reset sincrónico
            a_reg <= 4'b0;
            b_reg <= 4'b0;
            cin_reg <= 1'b0;
            sum_out <= 4'b0;
            cout_out <= 1'b0;
        end 
        else begin
            //Operación normal
            a_reg <= a_in;
            b_reg <= b_in;
            cin_reg <= cin_in;
            //Salidas
            sum_out  <= sum_temp[3:0];
            cout_out <= sum_temp[4];
        end
    end

endmodule

Modulo_Digital/Lab3/dv/tb_sumador_4b.v
`timescale 1ns/1ps

module tb_sumador_4b;

    reg clk_tb;
    reg rst_tb;
    reg [3:0] a_in_tb;
    reg [3:0] b_in_tb;
    reg cin_in_tb;
    wire [3:0] sum_out_tb;
    wire cout_out_tb;

    // Instancia del DUT (Device Under Test)
    sumador_4b uut (
        .clk(clk_tb),
        .rst(rst_tb),
        .a_in(a_in_tb),
        .b_in(b_in_tb),
        .cin_in(cin_in_tb),
        .sum_out(sum_out_tb),
        .cout_out(cout_out_tb)
    );

    // Generador de reloj: periodo de 10ns (100 MHz)
    always
    begin
        #5 clk_tb=!clk_tb;
    end

    // Proceso principal de estímulos
    initial begin
        $dumpfile("sumador_4b.vcd"); $dumpvars;

        // Inicialización
        clk_tb = 0;
        rst_tb = 1;
        a_in_tb = 4'b0000;
        b_in_tb = 4'b0000;
        cin_in_tb = 0;

        //Desactiva reset
        #15;
        rst_tb = 0;

        // Pruebas básicas
        #10; a_in_tb = 4'b0001; b_in_tb = 4'b0010; cin_in_tb = 0;  // 1 + 2 = 3
        #10; a_in_tb = 4'b0101; b_in_tb = 4'b0011; cin_in_tb = 0;  // 5 + 3 = 8
        #10; a_in_tb = 4'b1111; b_in_tb = 4'b0001; cin_in_tb = 0;  // 15 + 1 = 16 (carry)
        #10; a_in_tb = 4'b1010; b_in_tb = 4'b0101; cin_in_tb = 1;  // 10 + 5 + 1 = 16
        #10; a_in_tb = 4'b0110; b_in_tb = 4'b0110; cin_in_tb = 0;  // 6 + 6 = 12
        #10; a_in_tb = 4'b0111; b_in_tb = 4'b1001; cin_in_tb = 1;  // 7 + 9 + 1 = 17

        // Espera final
        #20;
        $finish;
    end

    // Monitoreo de señales
    initial begin
        $display("Tiempo | a_in | b_in | cin_in | sum_out | cout_out");
        $monitor("%4t |  %b  |  %b  |   %b   |   %b   |    %b",
                 $time, a_in_tb, b_in_tb, cin_in_tb, sum_out_tb, cout_out_tb);
    end

endmodule

Modulo_Digital/Lab2/sumador_4b.vcd
$date
	Tue Nov  4 09:31:41 2025
$end
$version
	Icarus Verilog
$end
$timescale
	1ps
$end
$scope module tb_sumador_4b $end
$var wire 4 ! sum_out_tb [3:0] $end
$var wire 1 " cout_out_tb $end
$var reg 4 # a_in_tb [3:0] $end
$var reg 4 $ b_in_tb [3:0] $end
$var reg 1 % cin_in_tb $end
$var reg 1 & clk_tb $end
$var reg 1 ' rst_tb $end
$scope module uut $end
$var wire 4 ( a_in [3:0] $end
$var wire 4 ) b_in [3:0] $end
$var wire 1 % cin_in $end
$var wire 1 & clk $end
$var wire 1 ' rst $end
$var wire 5 * sum_temp [4:0] $end
$var reg 4 + a_reg [3:0] $end
$var reg 4 , b_reg [3:0] $end
$var reg 1 - cin_reg $end
$var reg 1 " cout_out $end
$var reg 4 . sum_out [3:0] $end
$upscope $end
$upscope $end
$enddefinitions $end
$comment Show the parameter values. $end
$dumpall
$end
#0
$dumpvars
bx .
x-
bx ,
bx +
bx *
b0 )
b0 (
1'
0&
0%
b0 $
b0 #
x"
bx !
$end
#5000
b0 *
0"
b0 !
b0 .
0-
b0 ,
b0 +
1&
#10000
0&
#15000
1&
0'
#20000
0&
#25000
b11 *
b10 ,
b1 +
1&
b10 $
b10 )
b1 #
b1 (
#30000
0&
#35000
b1000 *
b11 !
b11 .
b11 ,
b101 +
1&
b11 $
b11 )
b101 #
b101 (
#40000
0&
#45000
b10000 *
b1000 !
b1000 .
b1 ,
b1111 +
1&
b1 $
b1 )
b1111 #
b1111 (
#50000
0&
#55000
b10000 *
1"
b0 !
b0 .
1-
b101 ,
b1010 +
1&
1%
b101 $
b101 )
b1010 #
b1010 (
#60000
0&
#65000
b1100 *
0-
b110 ,
b110 +
1&
0%
b110 $
b110 )
b110 #
b110 (
#70000
0&
#75000
b10001 *
0"
b1100 !
b1100 .
1-
b1001 ,
b111 +
1&
1%
b1001 $
b1001 )
b111 #
b111 (
#80000
0&
#85000
1"
b1 !
b1 .
1&
